neuronlens/README.md
neuronlens/__init__.py
neuronlens/api_client.py
neuronlens/config.json
neuronlens/config.py
neuronlens/engine.py
neuronlens/example_usage.py
neuronlens/test_simple.py
neuronlens-0.1.2.dist-info/METADATA
neuronlens-0.1.2.dist-info/WHEEL
neuronlens-0.1.2.dist-info/top_level.txt
neuronlens-0.1.2.dist-info/RECORD
