Metadata-Version: 2.4
Name: neuronlens
Version: 0.1.2
Summary: Python package for NeuronLens interpretability analysis
Author: NeuronLens Team
Classifier: Development Status :: 3 - Alpha
Classifier: Intended Audience :: Developers
Classifier: Intended Audience :: Science/Research
Classifier: License :: OSI Approved :: MIT License
Classifier: Programming Language :: Python :: 3
Classifier: Programming Language :: Python :: 3.8
Classifier: Programming Language :: Python :: 3.9
Classifier: Programming Language :: Python :: 3.10
Classifier: Programming Language :: Python :: 3.11
Requires-Python: >=3.8
Requires-Dist: requests>=2.31.0
Requires-Dist: numpy>=1.24.0
Provides-Extra: env
Requires-Dist: python-dotenv>=1.0.0; extra == "env"
Provides-Extra: all
Requires-Dist: python-dotenv>=1.0.0; extra == "all"
Dynamic: requires-python
